[
  {
    "transaction_type": "new",
    "file_name": "technical_manual_v1.pdf",
    "file_size": 5242880,
    "file_type": "application/pdf",
    "user_id": "user-001",
    "tags": "technical,manual,engineering",
    "description": "Technical manual for product X",
    "storage_path": "/documents/tech/manual_v1.pdf",
    "version": 1,
    "checksum": "abc123def456",
    "acl": "{\"read\": [\"user-001\", \"user-002\"], \"write\": [\"user-001\"]}",
    "thumbnail_path": "/thumbnails/tech_manual_v1.jpg",
    "expiration_date": "2026-12-31",
    "category": "Technical Documentation",
    "division": "Engineering",
    "business_unit": "Product Development",
    "brand_id": "brand-001",
    "document_type": "Manual",
    "region": "EMEA",
    "country": "Germany",
    "languages": "en,de",
    "alternate_part_numbers": "PN-001-A,PN-001-B"
  },
  {
    "transaction_type": "new",
    "file_name": "marketing_brochure.pdf",
    "file_size": 2097152,
    "file_type": "application/pdf",
    "user_id": "user-002",
    "tags": "marketing,sales,brochure",
    "description": "Marketing brochure for product launch",
    "storage_path": "/documents/marketing/brochure.pdf",
    "version": 1,
    "checksum": "def456ghi789",
    "acl": "{\"read\": [\"user-002\", \"user-003\"], \"write\": [\"user-002\"]}",
    "thumbnail_path": "/thumbnails/marketing_brochure.jpg",
    "expiration_date": "2025-06-30",
    "category": "Marketing Materials",
    "division": "Marketing",
    "business_unit": "Sales",
    "brand_id": "brand-002",
    "document_type": "Brochure",
    "region": "NA",
    "country": "USA",
    "languages": "en,es",
    "alternate_part_numbers": "PN-002-A"
  }
]
